easyregress/__init__.py
easyregress/easyregress.py
easyregress-0.0.1.dist-info/LICENSE
easyregress-0.0.1.dist-info/METADATA
easyregress-0.0.1.dist-info/WHEEL
easyregress-0.0.1.dist-info/top_level.txt
easyregress-0.0.1.dist-info/RECORD
